FuzzyClustering/ClusterAidedComputing.py
FuzzyClustering/ClusteringIteration.py
FuzzyClustering/FuzzyClustering.py
FuzzyClustering/__init__.py
FuzzyClustering-0.1.0.dist-info/LICENSE.txt
FuzzyClustering-0.1.0.dist-info/METADATA
FuzzyClustering-0.1.0.dist-info/WHEEL
FuzzyClustering-0.1.0.dist-info/top_level.txt
FuzzyClustering-0.1.0.dist-info/RECORD
