Metadata-Version: 2.1
Name: FuzzyClustering
Version: 0.1.0
Summary: Fuzzy clustering algorithm toolbox
Home-page: https://github.com/ChoiNgai/FuzzyClustering
Author: CAIWEI
Author-email: caiwei-email@qq.com
License: UNKNOWN
Project-URL: Bug Tracker, https://github.com/ChoiNgai/FuzzyClustering/issues
Platform: UNKNOWN
Classifier: Programming Language :: Python :: 3
Classifier: License :: OSI Approved :: MIT License
Classifier: Operating System :: OS Independent
Requires-Python: >=3.6
License-File: LICENSE.txt
